LICENSE.AGPL.md
LICENSE.md
README.md
setup.py
bin/rc_bootstrap.sh
src/rc.bootstrap.egg-info/PKG-INFO
src/rc.bootstrap.egg-info/SOURCES.txt
src/rc.bootstrap.egg-info/dependency_links.txt
src/rc.bootstrap.egg-info/namespace_packages.txt
src/rc.bootstrap.egg-info/not-zip-safe
src/rc.bootstrap.egg-info/requires.txt
src/rc.bootstrap.egg-info/top_level.txt
src/rc/bootstrap/SDIST
src/rc/bootstrap/VERSION
src/rc/bootstrap/__init__.py