Metadata-Version: 2.1
Name: rc.bootstrap
Version: 0.3.0
Summary: RC bootstrapper
Home-page: https://www.github.com/radical-consulting/rc.bootstrap/
Author: Andre Merzky
Author-email: andre.merzky@radical-consulting.com
Maintainer: RADICAL-Consulting UG
Maintainer-email: devel@radical-consulting.com
License: AGPL
Keywords: utilities
Platform: UNKNOWN
Classifier: Development Status :: 5 - Production/Stable
Classifier: Intended Audience :: Developers
Classifier: Environment :: Console
Classifier: License :: OSI Approved :: GNU Affero General Public License v3 or later (AGPLv3+)
Classifier: Programming Language :: Python
Classifier: Programming Language :: Python :: 3
Classifier: Programming Language :: Python :: 3.6
Classifier: Topic :: Utilities
Classifier: Topic :: System :: Distributed Computing
Classifier: Topic :: Scientific/Engineering
Classifier: Operating System :: MacOS :: MacOS X
Classifier: Operating System :: POSIX
Classifier: Operating System :: Unix
Requires-Python: >=3.6
License-File: LICENSE.AGPL.md
License-File: LICENSE.md
